README.md
setup.cfg
setup.py
ie_2018_groupB_yahoo_ks_datareader/KsDataReader.py
ie_2018_groupB_yahoo_ks_datareader/__init__.py
ie_2018_groupB_yahoo_ks_datareader.egg-info/PKG-INFO
ie_2018_groupB_yahoo_ks_datareader.egg-info/SOURCES.txt
ie_2018_groupB_yahoo_ks_datareader.egg-info/dependency_links.txt
ie_2018_groupB_yahoo_ks_datareader.egg-info/not-zip-safe
ie_2018_groupB_yahoo_ks_datareader.egg-info/top_level.txt