Metadata-Version: 1.0
Name: ie-2018-groupB-yahoo-ks-datareader
Version: 3.8
Summary: Python Packaging Starting Kit - Simple Structure to creater your own package - for training purposes!
Home-page: https://github.com/RimaNakhala/ie_2018_groupB_yahoo_ks_datareader
Author: rimanakhala
Author-email: rima.nakhala@student.ie.edu
License: MIT
Platform: UNKNOWN
